grayness_index/__init__.py
grayness_index/gi.py
grayness_index_python-0.0.2.dist-info/LICENSE
grayness_index_python-0.0.2.dist-info/METADATA
grayness_index_python-0.0.2.dist-info/WHEEL
grayness_index_python-0.0.2.dist-info/top_level.txt
grayness_index_python-0.0.2.dist-info/RECORD
