Metadata-Version: 2.1
Name: grayness-index-python
Version: 0.0.2
Summary: Python package for Grayness Index
Home-page: https://github.com/birdortyedi/grayness-index-python
Author: Furkan Kınlı
Author-email: furkan.kinli@ozyegin.edu.tr
Classifier: Programming Language :: Python :: 3
Classifier: License :: OSI Approved :: GNU Lesser General Public License v3 (LGPLv3)
Classifier: Operating System :: OS Independent
Requires-Python: >=3.6
License-File: LICENSE
Requires-Dist: numpy
Requires-Dist: scipy
Requires-Dist: glog
